otio_music_arrangement/__init__.py
otio_music_arrangement/builder.py
otio_music_arrangement/timing_utils.py
otio_music_arrangement-0.1.2.dist-info/METADATA
otio_music_arrangement-0.1.2.dist-info/WHEEL
otio_music_arrangement-0.1.2.dist-info/entry_points.txt
otio_music_arrangement-0.1.2.dist-info/top_level.txt
otio_music_arrangement-0.1.2.dist-info/RECORD
