Metadata-Version: 2.4
Name: otio-music-arrangement
Version: 0.1.2
Summary: Builds OpenTimelineIO timelines for music video editing workflows.
Project-URL: Homepage, https://github.com/allenday/otio-music-arrangement
Project-URL: Bug Tracker, https://github.com/allenday/otio-music-arrangement/issues
Classifier: Programming Language :: Python :: 3
Classifier: License :: OSI Approved :: MIT License
Classifier: Operating System :: OS Independent
Classifier: Topic :: Multimedia :: Video :: Non-Linear Editor
Classifier: Topic :: Software Development :: Libraries :: Python Modules
Requires-Python: >=3.10
Requires-Dist: opentimelineio>=0.15
Requires-Dist: ffmpeg-python>=0.2.0
Requires-Dist: librosa>=0.9
Requires-Dist: numpy
Requires-Dist: otio-fcpx-xml-lite-adapter>=0.1.2
Provides-Extra: test
Requires-Dist: pytest>=7.0; extra == "test"
Requires-Dist: pytest-cov; extra == "test"
Requires-Dist: pytest-mock; extra == "test"
Provides-Extra: dev
Requires-Dist: ruff>=0.1.0; extra == "dev"
Requires-Dist: mypy>=1.0; extra == "dev"
Requires-Dist: black>=23.0; extra == "dev"
Requires-Dist: isort>=5.0; extra == "dev"
Requires-Dist: pre-commit>=3.0; extra == "dev"
Requires-Dist: build; extra == "dev"
Requires-Dist: twine; extra == "dev"
